{
  "active": false,
  "connections": {
    "Scrape raw video URL": {
      "main": [
        [
          {
            "node": "Output video file without watermark",
            "type": "main",
            "index": 0
          }
        ]
      ]
    },
    "Get TikTok Video Page Data": {
      "main": [
        [
          {
            "node": "Scrape raw video URL",
            "type": "main",
            "index": 0
          }
        ]
      ]
    },
    "Output video file without watermark": {
      "main": [
        [
          {
            "node": "FTP",
            "type": "main",
            "index": 0
          }
        ]
      ]
    },
    "FTP": {
      "main": [
        [
          {
            "node": "Container HTTP Reels",
            "type": "main",
            "index": 0
          }
        ]
      ]
    },
    "⚙️ Configure Post Settings": {
      "main": [
        [
          {
            "node": "🔀 Smart Content Router",
            "type": "main",
            "index": 0
          }
        ]
      ]
    },
    "🔀 Smart Content Router": {
      "main": [
        [
          {
            "node": "Google Sheets — Read Rows4",
            "type": "main",
            "index": 0
          }
        ],
        [
          {
            "node": "Container FB Reels",
            "type": "main",
            "index": 0
          }
        ]
      ]
    },
    "Container HTTP Reels": {
      "main": [
        [
          {
            "node": "🔍 Check Processing Status",
            "type": "main",
            "index": 0
          }
        ]
      ]
    },
    "Container FB Reels": {
      "main": [
        [
          {
            "node": "🔍 Check Processing Status",
            "type": "main",
            "index": 0
          }
        ]
      ]
    },
    "🔍 Check Processing Status": {
      "main": [
        [
          {
            "node": "⏰ Initial Processing Wait",
            "type": "main",
            "index": 0
          }
        ]
      ]
    },
    "✅ Is Container Ready?": {
      "main": [
        [
          {
            "node": "🔀 HTTP vs FB API Router",
            "type": "main",
            "index": 0
          }
        ],
        [
          {
            "node": "anyError",
            "type": "main",
            "index": 0
          }
        ]
      ]
    },
    "🔀 HTTP vs FB API Router": {
      "main": [
        [
          {
            "node": "📤 Publish via HTTP API",
            "type": "main",
            "index": 0
          }
        ],
        [
          {
            "node": "📤 Publish via Facebook SDK",
            "type": "main",
            "index": 0
          }
        ]
      ]
    },
    "⏰ Initial Processing Wait": {
      "main": [
        [
          {
            "node": "🔍 Check Processing Status1",
            "type": "main",
            "index": 0
          }
        ]
      ]
    },
    "⏰ Retry Wait Loop": {
      "main": [
        [
          {
            "node": "🔍 Check Processing Status1",
            "type": "main",
            "index": 0
          }
        ]
      ]
    },
    "🔍 Check Processing Status1": {
      "main": [
        [
          {
            "node": "✅ Is Container Ready?",
            "type": "main",
            "index": 0
          }
        ]
      ]
    },
    "📤 Publish via HTTP API": {
      "main": [
        [
          {
            "node": "Update Sheet — SetStatus1",
            "type": "main",
            "index": 0
          }
        ]
      ]
    },
    "anyError": {
      "main": [
        [
          {
            "node": "UPDATE ERROR",
            "type": "main",
            "index": 0
          }
        ],
        [
          {
            "node": "⏰ Retry Wait Loop",
            "type": "main",
            "index": 0
          }
        ]
      ]
    },
    "Schedule Trigger": {
      "main": [
        [
          {
            "node": "⚙️ Configure Post Settings",
            "type": "main",
            "index": 0
          }
        ]
      ]
    },
    "Google Sheets — Read Rows4": {
      "main": [
        [
          {
            "node": "Get TikTok Video Page Data",
            "type": "main",
            "index": 0
          }
        ]
      ]
    }
  },
  "createdAt": "2025-09-10T08:19:35.554Z",
  "id": "B6TLIojlK1mmEm2G",
  "isArchived": true,
  "meta": {
    "templateCredsSetupCompleted": true
  },
  "name": "morph.tales1-instagram-extended",
  "nodes": [
    {
      "parameters": {
        "url": "={{ $json.DirectUrl }}",
        "sendHeaders": true,
        "headerParameters": {
          "parameters": [
            {
              "name": "User-Agent",
              "value": "Mozilla/5.0 (Windows NT 10.0; Win64; x64) Chrome/91.0.4472.124"
            }
          ]
        },
        "options": {
          "response": {
            "response": {
              "fullResponse": true,
              "responseFormat": "text"
            }
          }
        }
      },
      "id": "2bdbd146-97b0-4202-a8de-bf075209ab77",
      "name": "Get TikTok Video Page Data",
      "type": "n8n-nodes-base.httpRequest",
      "position": [
        -2448,
        -720
      ],
      "typeVersion": 4.2
    },
    {
      "parameters": {
        "jsCode": "const html = $input.first().json.data;\nconst headers = $input.first().json.headers || {};\nconst cookies = headers['set-cookie'] || [];\n\nif (!html) {\n  throw new Error(\"HTML body is undefined. Check the previous node's output.\");\n}\nconst regex = /<script id=\"__UNIVERSAL_DATA_FOR_REHYDRATION__\" type=\"application\\/json\">([\\s\\S]*?)<\\/script>/;\nconst match = html.match(regex);\n\nif (match) {\n  const jsonStr = match[1];\n  const data = JSON.parse(jsonStr);\n  const videoUrl = data?.__DEFAULT_SCOPE__?.[\"webapp.video-detail\"]?.itemInfo?.itemStruct?.video?.playAddr;\n  if (!videoUrl) {\n    throw new Error(\"Could not find video URL in the JSON data.\");\n  }\n  return [{ json: { videoUrl, cookies: cookies.join('; ') } }];\n} else {\n  throw new Error(\"Could not find __UNIVERSAL_DATA_FOR_REHYDRATION__ script in the HTML.\");\n}"
      },
      "id": "92748741-651f-415e-925f-e5e97237e420",
      "name": "Scrape raw video URL",
      "type": "n8n-nodes-base.code",
      "position": [
        -2224,
        -720
      ],
      "typeVersion": 2
    },
    {
      "parameters": {
        "operation": "appendOrUpdate",
        "documentId": {
          "__rl": true,
          "value": "1lBX-_Fm10zmUZvYOsGbVOG84z_kEfTSurt72FisNBX8",
          "mode": "list",
          "cachedResultName": "tiny.moew.diary-insta-tiktok",
          "cachedResultUrl": "https://docs.google.com/spreadsheets/d/1lBX-_Fm10zmUZvYOsGbVOG84z_kEfTSurt72FisNBX8/edit?usp=drivesdk"
        },
        "sheetName": {
          "__rl": true,
          "value": "gid=0",
          "mode": "list",
          "cachedResultName": "Sheet1",
          "cachedResultUrl": "https://docs.google.com/spreadsheets/d/1lBX-_Fm10zmUZvYOsGbVOG84z_kEfTSurt72FisNBX8/edit#gid=0"
        },
        "columns": {
          "mappingMode": "defineBelow",
          "value": {
            "DirectUrl": "={{ $('Google Sheets — Read Rows4').item.json.DirectUrl }}",
            "status": "=PUBLISHED"
          },
          "matchingColumns": [
            "DirectUrl"
          ],
          "schema": [
            {
              "id": "DirectUrl",
              "displayName": "DirectUrl",
              "required": false,
              "defaultMatch": false,
              "display": true,
              "type": "string",
              "canBeUsedToMatch": true,
              "removed": false
            },
            {
              "id": "status",
              "displayName": "status",
              "required": false,
              "defaultMatch": false,
              "display": true,
              "type": "string",
              "canBeUsedToMatch": true
            }
          ],
          "attemptToConvertTypes": false,
          "convertFieldsToString": false
        },
        "options": {}
      },
      "id": "872e0234-cbcd-42ef-8b0a-3240c58a8c92",
      "name": "Update Sheet — SetStatus1",
      "type": "n8n-nodes-base.googleSheets",
      "typeVersion": 4,
      "position": [
        16,
        -928
      ],
      "credentials": {
        "googleSheetsOAuth2Api": {
          "id": "H3U1X4hjIcv7PxVl",
          "name": "Google Sheets account"
        }
      }
    },
    {
      "parameters": {
        "url": "={{ $json.videoUrl }}",
        "sendHeaders": true,
        "headerParameters": {
          "parameters": [
            {
              "name": "User-Agent",
              "value": "Mozilla/5.0 (Windows NT 10.0; Win64; x64) AppleWebKit/537.36 (KHTML, like Gecko) Chrome/91.0.4472.124 Safari/537.36"
            },
            {
              "name": "Referer",
              "value": "https://www.tiktok.com/"
            },
            {
              "name": "Accept",
              "value": "video/mp4,video/webm,video/*;q=0.9,application/octet-stream;q=0.8"
            },
            {
              "name": "Accept-Language",
              "value": "en-US,en;q=0.5"
            },
            {
              "name": "Connection",
              "value": "keep-alive"
            },
            {
              "name": "Cookie",
              "value": "={{ $json.cookies }}"
            }
          ]
        },
        "options": {
          "allowUnauthorizedCerts": true,
          "response": {
            "response": {
              "responseFormat": "file"
            }
          }
        }
      },
      "id": "509e5932-6a36-4ebc-ba50-afd8bb2f0e4c",
      "name": "Output video file without watermark",
      "type": "n8n-nodes-base.httpRequest",
      "position": [
        -2000,
        -720
      ],
      "typeVersion": 4.2
    },
    {
      "parameters": {
        "protocol": "sftp",
        "operation": "upload",
        "path": "/upload/meow1/upload.mp4"
      },
      "type": "n8n-nodes-base.ftp",
      "typeVersion": 1,
      "position": [
        -1776,
        -720
      ],
      "id": "8f455ffb-87eb-435b-b40f-3d98b281ed28",
      "name": "FTP",
      "credentials": {
        "sftp": {
          "id": "C8w0MijZfYD2NPtq",
          "name": "SFTP"
        }
      }
    },
    {
      "parameters": {
        "assignments": {
          "assignments": [
            {
              "id": "217b69e3-98ec-49a2-8fde-372dd1bc1848",
              "name": "node",
              "value": "17841416753691295",
              "type": "string"
            },
            {
              "id": "2caebe7c-a2d3-428e-b129-fcfbe66854e5",
              "name": "post_type",
              "value": "http_reel",
              "type": "string"
            },
            {
              "id": "a17a5c94-d9ae-44f8-9d56-fb55d17efe5",
              "name": "image_url",
              "value": "https://cdn.pixabay.com/photo/2023/11/07/22/59/building-8373618_1280.jpg",
              "type": "string"
            },
            {
              "id": "32aa1561-458c-4f64-a854-eab65f9ad1dd",
              "name": "video_url",
              "value": "https://files.mohdasif.net/meow1/upload.mp4",
              "type": "string"
            },
            {
              "id": "c6485101-488b-43db-8708-1a1136292956",
              "name": "cover_image",
              "value": "https://cdn.pixabay.com/photo/2023/11/07/22/59/building-8373618_1280.jpg",
              "type": "string"
            }
          ]
        },
        "options": {}
      },
      "type": "n8n-nodes-base.set",
      "typeVersion": 3.4,
      "position": [
        -3120,
        -624
      ],
      "id": "ca644dea-b7dd-4b1d-8be3-f6d3c53de724",
      "name": "⚙️ Configure Post Settings"
    },
    {
      "parameters": {
        "rules": {
          "values": [
            {
              "conditions": {
                "options": {
                  "caseSensitive": true,
                  "leftValue": "",
                  "typeValidation": "strict",
                  "version": 2
                },
                "conditions": [
                  {
                    "id": "25e31619-4116-46e0-bfcb-a8d8a030fa68",
                    "leftValue": "={{ $json.post_type }}",
                    "rightValue": "http_reel",
                    "operator": {
                      "type": "string",
                      "operation": "equals",
                      "name": "filter.operator.equals"
                    }
                  }
                ],
                "combinator": "and"
              },
              "renameOutput": true,
              "outputKey": "HTTP - Reels"
            },
            {
              "conditions": {
                "options": {
                  "caseSensitive": true,
                  "leftValue": "",
                  "typeValidation": "strict",
                  "version": 2
                },
                "conditions": [
                  {
                    "id": "cf34e931-f798-4c70-af29-9aec7aab8f6c",
                    "leftValue": "={{ $json.post_type }}",
                    "rightValue": "fb_reel",
                    "operator": {
                      "type": "string",
                      "operation": "equals",
                      "name": "filter.operator.equals"
                    }
                  }
                ],
                "combinator": "and"
              },
              "renameOutput": true,
              "outputKey": "FB - Reels"
            }
          ]
        },
        "options": {}
      },
      "type": "n8n-nodes-base.switch",
      "typeVersion": 3.2,
      "position": [
        -2896,
        -624
      ],
      "id": "d02dca76-8c03-45f4-bb79-44257760d40b",
      "name": "🔀 Smart Content Router"
    },
    {
      "parameters": {
        "method": "POST",
        "url": "=https://graph.facebook.com/v22.0/{{ $('⚙️ Configure Post Settings').item.json.node }}/media",
        "authentication": "predefinedCredentialType",
        "nodeCredentialType": "facebookGraphApi",
        "sendQuery": true,
        "queryParameters": {
          "parameters": [
            {
              "name": "media_type",
              "value": "=REELS"
            },
            {
              "name": "video_url",
              "value": "={{ $('⚙️ Configure Post Settings').item.json.video_url }}"
            },
            {
              "name": "caption",
              "value": "={{ $('Google Sheets — Read Rows4').item.json.title }}"
            },
            {
              "name": "cover_url",
              "value": "="
            },
            {
              "name": "audio_name",
              "value": "={{ $('Google Sheets — Read Rows4').item.json.title }}"
            }
          ]
        },
        "options": {}
      },
      "type": "n8n-nodes-base.httpRequest",
      "typeVersion": 4.2,
      "position": [
        -1552,
        -720
      ],
      "id": "26664e3c-dae8-44f7-98f8-8e775b310b60",
      "name": "Container HTTP Reels",
      "credentials": {
        "facebookGraphApi": {
          "id": "IoWNonuo3DCqxU0n",
          "name": "tiny.moew.diary-instagram"
        }
      }
    },
    {
      "parameters": {
        "httpRequestMethod": "POST",
        "graphApiVersion": "v22.0",
        "node": "=17841456545908024",
        "edge": "media",
        "options": {
          "queryParameters": {
            "parameter": [
              {
                "name": "caption",
                "value": "={{ $json.caption }}"
              },
              {
                "name": "video_url",
                "value": "={{ $json.video_url }}"
              },
              {
                "name": "media_type",
                "value": "REELS"
              },
              {
                "name": "cover_url",
                "value": "={{ $json.cover_image }}"
              }
            ]
          }
        }
      },
      "type": "n8n-nodes-base.facebookGraphApi",
      "typeVersion": 1,
      "position": [
        -1552,
        -528
      ],
      "id": "e5e00e6e-dca2-4b47-9df8-f2dde9f9e052",
      "name": "Container FB Reels",
      "credentials": {
        "facebookGraphApi": {
          "id": "IoWNonuo3DCqxU0n",
          "name": "tiny.moew.diary-instagram"
        }
      }
    },
    {
      "parameters": {
        "assignments": {
          "assignments": [
            {
              "id": "37f96da8-a8b6-417b-b5cf-7a4df5b4610c",
              "name": "container_id",
              "value": "={{ $json.id }}",
              "type": "string"
            }
          ]
        },
        "options": {}
      },
      "type": "n8n-nodes-base.set",
      "typeVersion": 3.4,
      "position": [
        -1328,
        -624
      ],
      "id": "00826a7a-d41b-43c6-acb6-21bb1db93155",
      "name": "🔍 Check Processing Status"
    },
    {
      "parameters": {
        "conditions": {
          "options": {
            "caseSensitive": false,
            "leftValue": "",
            "typeValidation": "strict",
            "version": 2
          },
          "conditions": [
            {
              "id": "682def4c-2cda-4417-9329-682a8a60feed",
              "leftValue": "={{ $json.status_code }}",
              "rightValue": "FINISHED",
              "operator": {
                "type": "string",
                "operation": "equals",
                "name": "filter.operator.equals"
              }
            }
          ],
          "combinator": "and"
        },
        "options": {
          "ignoreCase": true
        }
      },
      "type": "n8n-nodes-base.if",
      "typeVersion": 2.2,
      "position": [
        -656,
        -688
      ],
      "id": "ce450363-ff65-4577-bf20-9393365a03e0",
      "name": "✅ Is Container Ready?"
    },
    {
      "parameters": {
        "conditions": {
          "options": {
            "caseSensitive": true,
            "leftValue": "",
            "typeValidation": "strict",
            "version": 2
          },
          "conditions": [
            {
              "id": "da6bcb63-632a-443a-b5b3-a8b6e1c62871",
              "leftValue": "={{ $('🔀 Smart Content Router').item.json.post_type.split(\"_\")[0] }}",
              "rightValue": "http",
              "operator": {
                "type": "string",
                "operation": "equals",
                "name": "filter.operator.equals"
              }
            }
          ],
          "combinator": "and"
        },
        "options": {}
      },
      "type": "n8n-nodes-base.if",
      "typeVersion": 2.2,
      "position": [
        -432,
        -832
      ],
      "id": "7b1c8909-264a-4919-bbc1-6997c6f8a247",
      "name": "🔀 HTTP vs FB API Router"
    },
    {
      "parameters": {
        "method": "POST",
        "url": "=https://graph.facebook.com/v22.0/{{ $('🔀 Smart Content Router').item.json.node }}/media_publish",
        "authentication": "predefinedCredentialType",
        "nodeCredentialType": "facebookGraphApi",
        "sendQuery": true,
        "queryParameters": {
          "parameters": [
            {
              "name": "creation_id",
              "value": "={{ $json.id }}"
            }
          ]
        },
        "options": {}
      },
      "type": "n8n-nodes-base.httpRequest",
      "typeVersion": 4.2,
      "position": [
        -208,
        -928
      ],
      "id": "a69d2b37-1913-48e7-9f8e-fc8400825cde",
      "name": "📤 Publish via HTTP API",
      "credentials": {
        "facebookGraphApi": {
          "id": "IoWNonuo3DCqxU0n",
          "name": "tiny.moew.diary-instagram"
        }
      }
    },
    {
      "parameters": {
        "httpRequestMethod": "POST",
        "graphApiVersion": "v22.0",
        "node": "={{ $('🔀 Smart Content Router').item.json.node }}",
        "edge": "media_publish",
        "options": {
          "queryParameters": {
            "parameter": [
              {
                "name": "creation_id",
                "value": "={{ $json.id }}"
              }
            ]
          }
        }
      },
      "type": "n8n-nodes-base.facebookGraphApi",
      "typeVersion": 1,
      "position": [
        -208,
        -736
      ],
      "id": "6d725c7e-653a-48a4-90f0-dfad76cdf5ba",
      "name": "📤 Publish via Facebook SDK",
      "credentials": {
        "facebookGraphApi": {
          "id": "IoWNonuo3DCqxU0n",
          "name": "tiny.moew.diary-instagram"
        }
      }
    },
    {
      "parameters": {},
      "type": "n8n-nodes-base.wait",
      "typeVersion": 1.1,
      "position": [
        -1104,
        -624
      ],
      "id": "958017e5-f98d-43b0-b974-c4673c9f539b",
      "name": "⏰ Initial Processing Wait",
      "webhookId": "443f84eb-1e9d-4c77-9a9a-c70290333dca"
    },
    {
      "parameters": {
        "amount": 15
      },
      "type": "n8n-nodes-base.wait",
      "typeVersion": 1.1,
      "position": [
        -208,
        -336
      ],
      "id": "17a13de0-e61b-4ed8-9698-4439947179df",
      "name": "⏰ Retry Wait Loop",
      "webhookId": "e9ac0c1d-b415-4160-a6b1-908d2310cb23"
    },
    {
      "parameters": {
        "url": "=https://graph.facebook.com/v22.0/{{ $('🔍 Check Processing Status').item.json.container_id }}",
        "authentication": "predefinedCredentialType",
        "nodeCredentialType": "facebookGraphApi",
        "sendQuery": true,
        "queryParameters": {
          "parameters": [
            {
              "name": "fields",
              "value": "status_code"
            }
          ]
        },
        "options": {}
      },
      "type": "n8n-nodes-base.httpRequest",
      "typeVersion": 4.2,
      "position": [
        -880,
        -624
      ],
      "id": "6ded3f41-ef8e-4c35-b81b-def0585e2d9f",
      "name": "🔍 Check Processing Status1",
      "credentials": {
        "facebookGraphApi": {
          "id": "IoWNonuo3DCqxU0n",
          "name": "tiny.moew.diary-instagram"
        }
      }
    },
    {
      "parameters": {
        "conditions": {
          "options": {
            "caseSensitive": false,
            "leftValue": "",
            "typeValidation": "strict",
            "version": 2
          },
          "conditions": [
            {
              "id": "682def4c-2cda-4417-9329-682a8a60feed",
              "leftValue": "={{ $json.status_code }}",
              "rightValue": "error",
              "operator": {
                "type": "string",
                "operation": "equals",
                "name": "filter.operator.equals"
              }
            }
          ],
          "combinator": "and"
        },
        "options": {
          "ignoreCase": true
        }
      },
      "type": "n8n-nodes-base.if",
      "typeVersion": 2.2,
      "position": [
        -432,
        -496
      ],
      "id": "98c798d0-22a4-4db3-9eb9-6a8de89adb8f",
      "name": "anyError"
    },
    {
      "parameters": {
        "operation": "appendOrUpdate",
        "documentId": {
          "__rl": true,
          "value": "1lBX-_Fm10zmUZvYOsGbVOG84z_kEfTSurt72FisNBX8",
          "mode": "list",
          "cachedResultName": "tiny.moew.diary-insta-tiktok",
          "cachedResultUrl": "https://docs.google.com/spreadsheets/d/1lBX-_Fm10zmUZvYOsGbVOG84z_kEfTSurt72FisNBX8/edit?usp=drivesdk"
        },
        "sheetName": {
          "__rl": true,
          "value": "gid=0",
          "mode": "list",
          "cachedResultName": "Sheet1",
          "cachedResultUrl": "https://docs.google.com/spreadsheets/d/1lBX-_Fm10zmUZvYOsGbVOG84z_kEfTSurt72FisNBX8/edit#gid=0"
        },
        "columns": {
          "mappingMode": "defineBelow",
          "value": {
            "DirectUrl": "={{ $('Google Sheets — Read Rows4').item.json.DirectUrl }}",
            "status": "=ERROR"
          },
          "matchingColumns": [
            "DirectUrl"
          ],
          "schema": [
            {
              "id": "DirectUrl",
              "displayName": "DirectUrl",
              "required": false,
              "defaultMatch": false,
              "display": true,
              "type": "string",
              "canBeUsedToMatch": true,
              "removed": false
            },
            {
              "id": "status",
              "displayName": "status",
              "required": false,
              "defaultMatch": false,
              "display": true,
              "type": "string",
              "canBeUsedToMatch": true
            }
          ],
          "attemptToConvertTypes": false,
          "convertFieldsToString": false
        },
        "options": {}
      },
      "id": "721d2fe1-e016-4ea4-a6f7-3c6f7643230a",
      "name": "UPDATE ERROR",
      "type": "n8n-nodes-base.googleSheets",
      "typeVersion": 4,
      "position": [
        -208,
        -544
      ],
      "credentials": {
        "googleSheetsOAuth2Api": {
          "id": "H3U1X4hjIcv7PxVl",
          "name": "Google Sheets account"
        }
      }
    },
    {
      "parameters": {
        "rule": {
          "interval": [
            {
              "field": "cronExpression",
              "expression": "0 8,13,20 * * *"
            }
          ]
        }
      },
      "type": "n8n-nodes-base.scheduleTrigger",
      "typeVersion": 1.2,
      "position": [
        -3312,
        -624
      ],
      "id": "516a7f99-d39c-4f3b-9197-f39a2de9ec23",
      "name": "Schedule Trigger"
    },
    {
      "parameters": {
        "documentId": {
          "__rl": true,
          "value": "1lBX-_Fm10zmUZvYOsGbVOG84z_kEfTSurt72FisNBX8",
          "mode": "list",
          "cachedResultName": "tiny.moew.diary-insta-tiktok",
          "cachedResultUrl": "https://docs.google.com/spreadsheets/d/1lBX-_Fm10zmUZvYOsGbVOG84z_kEfTSurt72FisNBX8/edit?usp=drivesdk"
        },
        "sheetName": {
          "__rl": true,
          "value": "gid=0",
          "mode": "list",
          "cachedResultName": "Sheet1",
          "cachedResultUrl": "https://docs.google.com/spreadsheets/d/1lBX-_Fm10zmUZvYOsGbVOG84z_kEfTSurt72FisNBX8/edit#gid=0"
        },
        "filtersUI": {
          "values": [
            {
              "lookupColumn": "status"
            }
          ]
        },
        "options": {}
      },
      "id": "9f0496dc-06cb-481b-a409-1996f70fbb53",
      "name": "Google Sheets — Read Rows4",
      "type": "n8n-nodes-base.googleSheets",
      "typeVersion": 4,
      "position": [
        -2672,
        -720
      ],
      "credentials": {
        "googleSheetsOAuth2Api": {
          "id": "H3U1X4hjIcv7PxVl",
          "name": "Google Sheets account"
        }
      }
    }
  ],
  "origin": "n8n",
  "pinData": {},
  "repo": {
    "owner": "hellomdasif",
    "name": "n8n-backup"
  },
  "settings": {
    "executionOrder": "v1"
  },
  "shared": [
    {
      "createdAt": "2025-09-10T08:19:35.559Z",
      "updatedAt": "2025-09-10T08:19:35.559Z",
      "role": "workflow:owner",
      "workflowId": "B6TLIojlK1mmEm2G",
      "projectId": "COQIBF46Vn0bg2e3"
    }
  ],
  "staticData": {
    "node:Schedule Trigger": {
      "recurrenceRules": []
    }
  },
  "tags": [
    {
      "createdAt": "2025-09-10T11:25:38.298Z",
      "updatedAt": "2025-09-10T11:25:38.298Z",
      "id": "r3ZdTHEV3fmr7eAz",
      "name": "instagram"
    }
  ],
  "triggerCount": 1,
  "updatedAt": "2025-10-06T13:01:54.000Z",
  "versionId": "1ccff44f-f9d5-466e-a77b-d68b08faf4db"
}